packer/__init__.py
packer/__main__.py
packer/__version__.py
packer/auth.py
packer/config.py
packer/export.py
packer/file_handling.py
packer/main.py
packer/redis_client.py
packer/task_status.py
packer/tasks.py
packer/jobs/__init__.py
packer/jobs/basic_export.py
packer/jobs/csr_export.py
packer/jobs/example.py
packer/table_transformations/__init__.py
packer/table_transformations/csr_transformations.py
packer/table_transformations/utils.py
transmart_packer-0.7.1.dist-info/LICENSE
transmart_packer-0.7.1.dist-info/METADATA
transmart_packer-0.7.1.dist-info/WHEEL
transmart_packer-0.7.1.dist-info/entry_points.txt
transmart_packer-0.7.1.dist-info/top_level.txt
transmart_packer-0.7.1.dist-info/RECORD
