Metadata-Version: 2.1
Name: transmart-packer
Version: 0.7.1
Summary: Data transformation jobs for TranSMART
Home-page: https://github.com/thehyve/transmart-packer
Author: Jochem Bijlard
Author-email: jochem@thehyve.nl
License: GNU General Public License v3 or later
Keywords: transmart-packer,transmart
Classifier: Development Status :: 2 - Pre-Alpha
Classifier: Intended Audience :: Developers
Classifier: Topic :: Scientific/Engineering :: Bio-Informatics
Classifier: License :: OSI Approved :: GNU General Public License (GPL)
Classifier: Natural Language :: English
Classifier: Programming Language :: Python :: 3
Classifier: Programming Language :: Python :: 3.7
Classifier: Programming Language :: Python :: 3.8
Classifier: Programming Language :: Python :: 3.9
Classifier: Programming Language :: Python :: 3.10
Requires-Python: >=3.7.0
License-File: LICENSE
Requires-Dist: PyYAML (==6.0)
Requires-Dist: transmart[full] (==0.2.7)
Requires-Dist: redis (<4.4,>=4.3.1)
Requires-Dist: celery (==5.2.6)
Requires-Dist: vine (==5.0.0)
Requires-Dist: tornado (<=6.1,>=6.0.4)
Requires-Dist: aioredis (<1.4.0,>=1.3.1)
Requires-Dist: cryptography (<37.1,>=37.0.2)
Requires-Dist: pyjwt (==2.4.0)
Requires-Dist: requests (<2.28.0,>=2.27.1)
Requires-Dist: pandas (==1.3.5)
Requires-Dist: numpy (<1.23,>=1.21.6)
Provides-Extra: dev
Requires-Dist: prospector[with_pyroma] ; extra == 'dev'
Requires-Dist: pygments ; extra == 'dev'
Requires-Dist: yapf ; extra == 'dev'
Requires-Dist: isort ; extra == 'dev'
